{
  "app": [
    {
      "definition": {
        "appV2": {
          "id": "17d433ca-d6e1-4316-bd1d-bbb04c812b5d",
          "type": "front-end",
          "name": "hitchcock",
          "slug": "17d433ca-d6e1-4316-bd1d-bbb04c812b5d",
          "isPublic": false,
          "isMaintenanceOn": false,
          "icon": "server",
          "organizationId": "34f4456d-81d7-4d69-b5d3-43e309664838",
          "currentVersionId": "ad577df9-5267-4846-8f0f-29b44cc89d20",
          "userId": "b7d10b9a-8e4f-4452-bad8-7acd25764168",
          "workflowApiToken": null,
          "workflowEnabled": false,
          "isInitialisedFromPrompt": false,
          "appGeneratedFromPrompt": false,
          "appBuilderMode": "visual",
          "aiGenerationMetadata": null,
          "createdAt": "2025-12-02T12:10:29.543Z",
          "creationMode": "DEFAULT",
          "updatedAt": "2025-12-02T12:59:46.765Z",
          "__loaded": true,
          "editingVersion": {
            "id": "634f9169-5c73-4bb0-a778-1f81ee0b583b",
            "name": "v2",
            "definition": null,
            "globalSettings": {
              "appInMaintenance": false,
              "canvasMaxWidth": 100,
              "canvasMaxWidthType": "%",
              "canvasMaxHeight": 2400,
              "canvasBackgroundColor": "var(--cc-appBackground-surface)",
              "backgroundFxQuery": "",
              "appMode": "auto"
            },
            "pageSettings": {
              "properties": {
                "disableMenu": {
                  "value": "{{false}}",
                  "fxActive": false
                }
              }
            },
            "showViewerNavigation": true,
            "homePageId": "54efe323-f6ad-4b39-9793-2d60e6801241",
            "appId": "17d433ca-d6e1-4316-bd1d-bbb04c812b5d",
            "currentEnvironmentId": "0aa9eb81-1f66-4363-90bc-42f91f700ec0",
            "promotedFrom": null,
            "parentVersionId": null,
            "status": "PUBLISHED",
            "description": "",
            "publishedAt": null,
            "releasedAt": null,
            "createdAt": "2025-12-02T12:39:17.581Z",
            "updatedAt": "2025-12-02T13:00:10.677Z"
          },
          "components": [
            {
              "id": "7898c925-6d7b-4440-81c3-c0a68d0f7a3b",
              "name": "table1",
              "type": "Table",
              "pageId": "54efe323-f6ad-4b39-9793-2d60e6801241",
              "parent": null,
              "properties": {
                "title": {
                  "value": "Table"
                },
                "visible": {
                  "value": "{{true}}"
                },
                "loadingState": {
                  "value": "{{false}}"
                },
                "dataSourceSelector": {
                  "value": "rawJson"
                },
                "data": {
                  "value": "{{ [ \n\t\t{ id: 1, name: 'Olivia Nguyen', email: 'olivia.nguyen@example.com', date: '15/05/2022', phone: 9876543210, interest: ['Reading', 'Traveling','Photography'], photo: 'https://reqres.in/img/faces/7-image.jpg' }, \n\t\t{ id: 2, name: 'Liam Patel', email: 'liam.patel@example.com', date: '20/09/2021', phone: 8765432109, interest: ['Cooking','Gardening','Hiking'], photo: 'https://reqres.in/img/faces/5-image.jpg' }, \n\t\t{ id: 3, name: 'Sophia Reyes', email: 'sophia.reyes@example.com', date: '01/01/2023', phone: 7654321098, interest: ['Music','Dancing','Crafting'], photo: 'https://reqres.in/img/faces/3-image.jpg' }, \n\t\t{ id: 4, name: 'Jacob Hernandez', email: 'jacob.hernandez@example.com', date: '10/11/2022', phone: 6543210987, interest: ['Reading', 'Traveling', 'Volunteering'], photo: 'https://reqres.in/img/faces/1-image.jpg' }, \n\t\t{ id: 5, name: 'William Sanchez', email: 'william.sanchez@example.com', date: '07/01/2021', phone: 4321098765, interest: ['Music', 'Dancing', 'Hiking'], photo: 'https://reqres.in/img/faces/4-image.jpg' }, \n\t\t{ id: 6, name: 'Ethan Morales', email: 'ethan.morales@example.com', date: '05/11/2021', phone: 2109876543, interest: ['Cooking', 'Traveling', 'Photography'], photo: 'https://reqres.in/img/faces/6-image.jpg' }, \n\t\t{ id: 7, name: 'Mia Tiana', email: 'mia.tiana@example.com', date: '21/11/2022', phone: 1098705217, interest: ['Music', 'Gardening', 'Hiking'], photo: 'https://reqres.in/img/faces/2-image.jpg' }, \n\t\t{ id: 8, name: 'Lucas Ramirez', email: 'lucas.ramirez@example.com', date: '31/03/2023', phone: 9876543210, interest: ['Reading', 'Dancing', 'Crafting'], photo: 'https://reqres.in/img/faces/9-image.jpg' }, \n\t\t{ id: 9, name: 'Alexander Vela', email: 'alexander.vela@example.com', date: '07/09/2022', phone: 7654321098, interest: ['Music','Gardening','Photography'], photo: 'https://reqres.in/img/faces/8-image.jpg' }, \n\t\t{ id: 10, name: 'Michael Reyes', email: 'michael.reyes@example.com', date: '25/12/2021', phone: 5432109876, interest: ['Cooking','Crafting','Volunteering'], photo: 'https://reqres.in/img/faces/10-image.jpg' } \n] }}"
                },
                "useDynamicColumn": {
                  "value": "{{false}}"
                },
                "columnData": {
                  "value": "{{[{name: 'email', key: 'email', id: '1'}, {name: 'Full name', key: 'name', id: '2', isEditable: true}]}}"
                },
                "rowsPerPage": {
                  "value": "{{10}}"
                },
                "serverSidePagination": {
                  "value": "{{false}}"
                },
                "enableNextButton": {
                  "value": "{{true}}"
                },
                "enablePrevButton": {
                  "value": "{{true}}"
                },
                "totalRecords": {
                  "value": "{{10}}"
                },
                "enablePagination": {
                  "value": "{{true}}"
                },
                "serverSideSort": {
                  "value": "{{false}}"
                },
                "serverSideFilter": {
                  "value": "{{false}}"
                },
                "displaySearchBox": {
                  "value": "{{true}}"
                },
                "showDownloadButton": {
                  "value": "{{true}}"
                },
                "showFilterButton": {
                  "value": "{{true}}"
                },
                "autogenerateColumns": {
                  "value": true,
                  "generateNestedColumns": true
                },
                "isAllColumnsEditable": {
                  "value": "{{false}}"
                },
                "columns": {
                  "value": [
                    {
                      "name": "id",
                      "key": "id",
                      "id": "e3ecbf7fa52c4d7210a93edb8f43776267a489bad52bd108be9588f790126737",
                      "autogenerated": true,
                      "fxActiveFields": [],
                      "columnSize": 30,
                      "columnType": "string"
                    },
                    {
                      "name": "photo",
                      "key": "photo",
                      "id": "f23b7d134b2e490ea41e3bb8eeb8c8e37472af243bf6b70d5af294482097e3a2",
                      "autogenerated": true,
                      "fxActiveFields": [],
                      "columnType": "image",
                      "objectFit": "contain",
                      "borderRadius": "100",
                      "columnSize": 70
                    },
                    {
                      "name": "name",
                      "key": "name",
                      "id": "5d2a3744a006388aadd012fcc15cc0dbcb5f9130e0fbb64c558561c97118754a",
                      "autogenerated": true,
                      "fxActiveFields": [],
                      "columnSize": 130,
                      "columnType": "string"
                    },
                    {
                      "name": "email",
                      "key": "email",
                      "id": "afc9a5091750a1bd4760e38760de3b4be11a43452ae8ae07ce2eebc569fe9a7f",
                      "autogenerated": true,
                      "fxActiveFields": [],
                      "columnSize": 230,
                      "columnType": "string"
                    },
                    {
                      "name": "date",
                      "key": "date",
                      "id": "27b75c8af9d34d1eaa1f9bb7f8f9f7b0abf1823e799748c8bb57e74f53b2c1dc",
                      "autogenerated": true,
                      "fxActiveFields": [],
                      "columnType": "datepicker",
                      "isTimeChecked": false,
                      "dateFormat": "DD/MM/YYYY",
                      "parseDateFormat": "DD/MM/YYYY",
                      "isDateSelectionEnabled": true,
                      "columnSize": 130
                    },
                    {
                      "name": "interest",
                      "key": "interest",
                      "id": "f23b7d134b2e490ea41e3bb8eeb8c8e37472af243bf6b70d5af294482097e3a1",
                      "autogenerated": true,
                      "fxActiveFields": [],
                      "columnType": "newMultiSelect",
                      "columnSize": 300,
                      "options": [
                        {
                          "label": "Reading",
                          "value": "Reading"
                        },
                        {
                          "label": "Traveling",
                          "value": "Traveling"
                        },
                        {
                          "label": "Photography",
                          "value": "Photography"
                        },
                        {
                          "label": "Music",
                          "value": "Music"
                        },
                        {
                          "label": "Cooking",
                          "value": "Cooking"
                        },
                        {
                          "label": "Crafting",
                          "value": "Crafting"
                        },
                        {
                          "label": "Volunteering",
                          "value": "Volunteering"
                        },
                        {
                          "label": "Gardening",
                          "value": "Gardening"
                        },
                        {
                          "label": "Dancing",
                          "value": "Dancing"
                        },
                        {
                          "label": "Hiking",
                          "value": "Hiking"
                        }
                      ]
                    },
                    {
                      "id": "99632bd1-e3a0-4451-b1b6-1936519ad5f1",
                      "name": "phone",
                      "key": "phone",
                      "columnType": "number",
                      "autogenerated": true
                    }
                  ]
                },
                "showBulkUpdateActions": {
                  "value": "{{true}}"
                },
                "showBulkSelector": {
                  "value": "{{false}}"
                },
                "highlightSelectedRow": {
                  "value": "{{false}}"
                },
                "columnSizes": {
                  "value": "{{({})}}"
                },
                "actions": {
                  "value": []
                },
                "enabledSort": {
                  "value": "{{true}}"
                },
                "hideColumnSelectorButton": {
                  "value": "{{false}}"
                },
                "defaultSelectedRow": {
                  "value": "{{{\"id\":1}}}"
                },
                "showAddNewRowButton": {
                  "value": "{{true}}"
                },
                "allowSelection": {
                  "value": "{{true}}"
                },
                "visibility": {
                  "value": "{{true}}"
                },
                "disabledState": {
                  "value": "{{false}}"
                },
                "dynamicHeight": {
                  "value": "{{false}}"
                },
                "selectRowOnCellEdit": {
                  "value": "{{false}}"
                }
              },
              "general": {},
              "styles": {
                "columnTitleColor": {
                  "value": "var(--cc-placeholder-text)"
                },
                "columnBackgroundColor": {
                  "value": "var(--cc-surface2-surface)"
                },
                "containerBackgroundColor": {
                  "value": "var(--cc-surface1-surface)"
                },
                "textColor": {
                  "value": "var(--cc-primary-text)"
                },
                "columnHeaderWrap": {
                  "value": "fixed"
                },
                "headerCasing": {
                  "value": "uppercase"
                },
                "actionButtonRadius": {
                  "value": "0"
                },
                "cellSize": {
                  "value": "regular"
                },
                "borderRadius": {
                  "value": "6"
                },
                "borderColor": {
                  "value": "var(--cc-default-border)"
                },
                "tableType": {
                  "value": "table-classic"
                },
                "maxRowHeight": {
                  "value": "auto"
                },
                "maxRowHeightValue": {
                  "value": "{{0}}"
                },
                "contentWrap": {
                  "value": "{{true}}"
                },
                "boxShadow": {
                  "value": "0px 0px 0px 0px #00000090"
                },
                "padding": {
                  "value": "default"
                }
              },
              "generalStyles": {
                "boxShadow": {
                  "value": "0px 0px 0px 0px #00000040"
                }
              },
              "displayPreferences": {
                "showOnDesktop": {
                  "value": "{{true}}"
                },
                "showOnMobile": {
                  "value": "{{false}}"
                }
              },
              "validation": {},
              "createdAt": "2025-12-02T12:39:16.701Z",
              "updatedAt": "2025-12-02T13:00:13.171Z",
              "layouts": [
                {
                  "id": "1f2e8f59-b9d4-4c3e-91ee-b3873b3a4cc7",
                  "type": "mobile",
                  "top": 160,
                  "left": 2,
                  "width": 25,
                  "height": 460,
                  "componentId": "7898c925-6d7b-4440-81c3-c0a68d0f7a3b",
                  "dimensionUnit": "count",
                  "updatedAt": "2025-12-02T12:39:16.701Z"
                },
                {
                  "id": "d3978a8e-4b79-45e2-9f81-5248690e953d",
                  "type": "desktop",
                  "top": 160,
                  "left": 2,
                  "width": 16,
                  "height": 460,
                  "componentId": "7898c925-6d7b-4440-81c3-c0a68d0f7a3b",
                  "dimensionUnit": "count",
                  "updatedAt": "2025-12-02T12:39:16.701Z"
                }
              ]
            },
            {
              "id": "f581809c-fda7-49f4-8556-7fa56957886c",
              "name": "chart1",
              "type": "Chart",
              "pageId": "54efe323-f6ad-4b39-9793-2d60e6801241",
              "parent": null,
              "properties": {
                "title": {
                  "value": "This title can be changed"
                },
                "markerColor": {
                  "value": "var(--cc-primary-brand)"
                },
                "showAxes": {
                  "value": "{{true}}"
                },
                "showGridLines": {
                  "value": "{{true}}"
                },
                "plotFromJson": {
                  "value": "{{false}}"
                },
                "loadingState": {
                  "value": "{{false}}"
                },
                "barmode": {
                  "value": "group"
                },
                "jsonDescription": {
                  "value": "{\n              \"data\": [\n                  {\n                      \"x\": [\n                          \"Jan\",\n                          \"Feb\",\n                          \"Mar\"\n                      ],\n                      \"y\": [\n                          100,\n                          80,\n                          40\n                      ],\n                      \"type\": \"bar\"\n                  }\n              ]\n          }"
                },
                "type": {
                  "value": "line"
                },
                "data": {
                  "value": "[\n    { \"x\": \"Jan\", \"y\": 100},\n    { \"x\": \"Feb\", \"y\": 80},\n    { \"x\": \"Mar\", \"y\": 40}\n  ]"
                }
              },
              "general": {},
              "styles": {
                "backgroundColor": {
                  "value": "var(--cc-surface1-surface)"
                },
                "padding": {
                  "value": "50"
                },
                "borderRadius": {
                  "value": "{{6}}"
                },
                "visibility": {
                  "value": "{{true}}"
                },
                "disabledState": {
                  "value": "{{false}}"
                },
                "borderColor": {
                  "value": "var(--cc-default-border)"
                }
              },
              "generalStyles": {
                "boxShadow": {
                  "value": "0px 0px 0px 0px #00000040"
                }
              },
              "displayPreferences": {
                "showOnDesktop": {
                  "value": "{{true}}"
                },
                "showOnMobile": {
                  "value": "{{false}}"
                }
              },
              "validation": {},
              "createdAt": "2025-12-02T12:39:16.701Z",
              "updatedAt": "2025-12-02T12:39:16.701Z",
              "layouts": [
                {
                  "id": "f55888bc-72b7-489a-85bd-6d0ef951eac9",
                  "type": "desktop",
                  "top": 670,
                  "left": 2,
                  "width": 20,
                  "height": 400,
                  "componentId": "f581809c-fda7-49f4-8556-7fa56957886c",
                  "dimensionUnit": "count",
                  "updatedAt": "2025-12-02T12:39:16.701Z"
                },
                {
                  "id": "34ca8682-9d5b-44c4-9727-4c827883ac28",
                  "type": "mobile",
                  "top": 670,
                  "left": 2,
                  "width": 20,
                  "height": 400,
                  "componentId": "f581809c-fda7-49f4-8556-7fa56957886c",
                  "dimensionUnit": "count",
                  "updatedAt": "2025-12-02T12:39:16.701Z"
                }
              ]
            }
          ],
          "pages": [
            {
              "id": "54efe323-f6ad-4b39-9793-2d60e6801241",
              "name": "Home",
              "handle": "home",
              "index": 1,
              "disabled": false,
              "hidden": false,
              "icon": null,
              "createdAt": "2025-12-02T12:39:16.701Z",
              "updatedAt": "2025-12-02T12:39:16.701Z",
              "autoComputeLayout": true,
              "appVersionId": "634f9169-5c73-4bb0-a778-1f81ee0b583b",
              "pageGroupIndex": 1,
              "pageGroupId": null,
              "isPageGroup": false,
              "url": null,
              "openIn": "new_tab",
              "type": "default",
              "appId": ""
            }
          ],
          "events": [],
          "dataQueries": [
            {
              "id": "7779bb1e-5ecb-45ce-9cb8-5eed164eef61",
              "name": "tooljetdb1",
              "options": {
                "operation": "",
                "transformationLanguage": "javascript",
                "enableTransformation": false,
                "organization_id": "34f4456d-81d7-4d69-b5d3-43e309664838"
              },
              "dataSourceId": "7b97a239-b763-46c7-8d27-024579060d36",
              "appVersionId": "634f9169-5c73-4bb0-a778-1f81ee0b583b",
              "createdAt": "2025-12-02T12:39:16.701Z",
              "updatedAt": "2025-12-02T12:39:16.701Z"
            }
          ],
          "dataSources": [
            {
              "id": "7b97a239-b763-46c7-8d27-024579060d36",
              "name": "tooljetdbdefault",
              "kind": "tooljetdb",
              "type": "static",
              "pluginId": null,
              "appVersionId": null,
              "organizationId": "34f4456d-81d7-4d69-b5d3-43e309664838",
              "scope": "global",
              "createdAt": "2025-12-02T10:33:41.696Z",
              "updatedAt": "2025-12-02T10:33:41.696Z"
            }
          ],
          "appVersions": [
            {
              "id": "634f9169-5c73-4bb0-a778-1f81ee0b583b",
              "name": "v2",
              "definition": null,
              "globalSettings": {
                "appInMaintenance": false,
                "canvasMaxWidth": 100,
                "canvasMaxWidthType": "%",
                "canvasMaxHeight": 2400,
                "canvasBackgroundColor": "var(--cc-appBackground-surface)",
                "backgroundFxQuery": "",
                "appMode": "auto"
              },
              "pageSettings": {
                "properties": {
                  "disableMenu": {
                    "value": "{{false}}",
                    "fxActive": false
                  }
                }
              },
              "showViewerNavigation": true,
              "homePageId": "54efe323-f6ad-4b39-9793-2d60e6801241",
              "appId": "17d433ca-d6e1-4316-bd1d-bbb04c812b5d",
              "currentEnvironmentId": "0aa9eb81-1f66-4363-90bc-42f91f700ec0",
              "promotedFrom": null,
              "parentVersionId": null,
              "status": "PUBLISHED",
              "description": "",
              "publishedAt": null,
              "releasedAt": null,
              "createdAt": "2025-12-02T12:39:17.581Z",
              "updatedAt": "2025-12-02T13:00:10.677Z"
            }
          ],
          "appEnvironments": [
            {
              "id": "b09c820d-30b9-4f56-ac65-16f0cdeea9e7",
              "organizationId": "34f4456d-81d7-4d69-b5d3-43e309664838",
              "name": "development",
              "isDefault": false,
              "priority": 1,
              "enabled": true,
              "createdAt": "2025-12-02T10:33:41.177Z",
              "updatedAt": "2025-12-02T10:33:41.177Z"
            },
            {
              "id": "0aa9eb81-1f66-4363-90bc-42f91f700ec0",
              "organizationId": "34f4456d-81d7-4d69-b5d3-43e309664838",
              "name": "staging",
              "isDefault": false,
              "priority": 2,
              "enabled": true,
              "createdAt": "2025-12-02T10:33:41.198Z",
              "updatedAt": "2025-12-02T10:33:41.198Z"
            },
            {
              "id": "f61c28e3-cf43-40a7-ae94-0ed3b7462c59",
              "organizationId": "34f4456d-81d7-4d69-b5d3-43e309664838",
              "name": "production",
              "isDefault": true,
              "priority": 3,
              "enabled": true,
              "createdAt": "2025-12-02T10:33:41.206Z",
              "updatedAt": "2025-12-02T10:33:41.206Z"
            }
          ],
          "dataSourceOptions": [
            {
              "id": "cf07a97c-5a07-4ebb-b01e-96c2c996d991",
              "dataSourceId": "7b97a239-b763-46c7-8d27-024579060d36",
              "environmentId": "0aa9eb81-1f66-4363-90bc-42f91f700ec0",
              "options": null,
              "createdAt": "2025-12-02T10:33:41.703Z",
              "updatedAt": "2025-12-02T10:33:41.703Z"
            },
            {
              "id": "5bc5e9a6-1b70-4414-a0b1-441051a8d71a",
              "dataSourceId": "7b97a239-b763-46c7-8d27-024579060d36",
              "environmentId": "b09c820d-30b9-4f56-ac65-16f0cdeea9e7",
              "options": null,
              "createdAt": "2025-12-02T10:33:41.703Z",
              "updatedAt": "2025-12-02T10:33:41.703Z"
            },
            {
              "id": "d140502b-d512-4cb9-bbbf-f7eed9a54fc5",
              "dataSourceId": "7b97a239-b763-46c7-8d27-024579060d36",
              "environmentId": "f61c28e3-cf43-40a7-ae94-0ed3b7462c59",
              "options": null,
              "createdAt": "2025-12-02T10:33:41.703Z",
              "updatedAt": "2025-12-02T10:33:41.703Z"
            }
          ],
          "schemaDetails": {
            "multiPages": true,
            "multiEnv": true,
            "globalDataSources": true
          },
          "modules": []
        }
      }
    }
  ],
  "tooljet_version": "3.20.45-cloud-lts"
}