{
  "id": "34855936-2292-4149-ad3d-3822ef7a9ffa",
  "options": {
    "host": {
      "encrypted": true,
      "credential_id": "adfbf770-9753-47d4-8a0f-f4c0d094477f"
    },
    "port": {
      "encrypted": true,
      "credential_id": "da51d4f9-4047-4eef-a094-4837c7773e8e"
    },
    "database": {
      "value": "sample_db",
      "encrypted": false
    },
    "password": {
      "encrypted": true,
      "credential_id": "0c7cf555-717b-4ee3-a4c8-e63ce27fe0a6"
    },
    "username": {
      "encrypted": true,
      "credential_id": "0001e889-cbf8-4151-adc6-fd5816bbbaa9"
    },
    "ssl_enabled": {
      "value": false,
      "encrypted": false
    },
    "connection_type": {
      "value": "manual",
      "encrypted": false
    },
    "ssl_certificate": {
      "value": "none",
      "encrypted": false
    }
  },
  "environmentId": "0c0c366e-688e-4aa3-8fb8-59159965668d",
  "dataSourceId": "9f7fef10-be1f-4053-bcb0-5906b025c2de",
  "createdAt": "2026-04-10T08:30:04.194Z",
  "updatedAt": "2026-04-10T08:30:04.194Z"
}