{
  "id": "8799028d-9251-4953-8390-bacd28afe5be",
  "options": {
    "url": {
      "value": "https://jsonplaceholder.typicode.com/users",
      "encrypted": false
    },
    "scopes": {
      "value": "read, write",
      "encrypted": false
    },
    "headers": {
      "value": [
        [
          "",
          ""
        ]
      ],
      "encrypted": false
    },
    "audience": {
      "value": "",
      "encrypted": false
    },
    "auth_url": {
      "value": "",
      "encrypted": false
    },
    "username": {
      "value": "",
      "encrypted": false
    },
    "auth_type": {
      "value": "none",
      "encrypted": false
    },
    "client_id": {
      "value": "",
      "encrypted": false
    },
    "grant_type": {
      "value": "authorization_code",
      "encrypted": false
    },
    "client_auth": {
      "value": "body",
      "encrypted": false
    },
    "add_token_to": {
      "value": "header",
      "encrypted": false
    },
    "header_prefix": {
      "value": "Bearer ",
      "encrypted": false
    },
    "ssl_certificate": {
      "value": "none",
      "encrypted": false
    },
    "access_token_url": {
      "value": "",
      "encrypted": false
    },
    "custom_auth_params": {
      "value": [
        [
          "",
          ""
        ]
      ],
      "encrypted": false
    },
    "custom_query_params": {
      "value": [
        [
          "",
          ""
        ]
      ],
      "encrypted": false
    },
    "retry_network_errors": {
      "value": true,
      "encrypted": false
    },
    "multiple_auth_enabled": {
      "value": false,
      "encrypted": false
    },
    "access_token_custom_headers": {
      "value": [
        [
          "",
          ""
        ]
      ],
      "encrypted": false
    }
  },
  "environmentId": "0db952b5-ab93-4dd5-b100-050d393f6879",
  "dataSourceId": "e4a60631-bc04-4cd3-8839-69b30252f82d",
  "createdAt": "2026-04-21T06:09:35.956Z",
  "updatedAt": "2026-04-21T07:03:55.529Z"
}